DukeDS/__init__.py
ddsc/__init__.py
ddsc/__main__.py
ddsc/cmdparser.py
ddsc/config.py
ddsc/ddsclient.py
ddsc/exceptions.py
ddsc/generatedocs.py
ddsc/versioncheck.py
ddsc/azure/__init__.py
ddsc/azure/__main__.py
ddsc/azure/api.py
ddsc/azure/azcopy.py
ddsc/azure/commands.py
ddsc/azure/delivery.py
ddsc/azure/exceptions.py
ddsc/core/__init__.py
ddsc/core/consistency.py
ddsc/core/d4s2.py
ddsc/core/ddsapi.py
ddsc/core/download.py
ddsc/core/fileuploader.py
ddsc/core/ignorefile.py
ddsc/core/localstore.py
ddsc/core/moveutil.py
ddsc/core/parallel.py
ddsc/core/pathfilter.py
ddsc/core/projectuploader.py
ddsc/core/remotestore.py
ddsc/core/retry.py
ddsc/core/upload.py
ddsc/core/userutil.py
ddsc/core/util.py
ddsc/sdk/__init__.py
ddsc/sdk/client.py
ddsc/sdk/dukeds.py
DukeDSClient-4.0.0.dist-info/LICENSE
DukeDSClient-4.0.0.dist-info/METADATA
DukeDSClient-4.0.0.dist-info/WHEEL
DukeDSClient-4.0.0.dist-info/entry_points.txt
DukeDSClient-4.0.0.dist-info/top_level.txt
DukeDSClient-4.0.0.dist-info/RECORD
